tai_test_utils/__init__.py
tai_test_utils/version.py
tai_test_utils/datasets/__init__.py
tai_test_utils/datasets/tabular/__init__.py
tai_test_utils/datasets/tabular/classification_data_utils.py
tai_test_utils/datasets/tabular/regression_data_utils.py
tai_test_utils/datasets/tabular/timeseries_data_utils.py
tai_test_utils/datasets/vision/__init__.py
tai_test_utils/datasets/vision/object_detection_data_utils.py
tai_test_utils/models/__init__.py
tai_test_utils/models/model_utils.py
tai_test_utils/models/lightgbm/__init__.py
tai_test_utils/models/lightgbm/lightgbm_model_utils.py
tai_test_utils/models/sklearn/__init__.py
tai_test_utils/models/sklearn/sklearn_model_utils.py
tai_test_utils/models/torch/__init__.py
tai_test_utils/models/torch/torch_model_utils.py
tai_test_utils/models/xgboost/__init__.py
tai_test_utils/models/xgboost/xgboost_model_utils.py
tai_test_utils/utilities/__init__.py
tai_test_utils/utilities/utils.py
tai_test_utils-0.4.4.dist-info/LICENSE
tai_test_utils-0.4.4.dist-info/METADATA
tai_test_utils-0.4.4.dist-info/WHEEL
tai_test_utils-0.4.4.dist-info/top_level.txt
tai_test_utils-0.4.4.dist-info/RECORD
